termplotlib/__init__.py
termplotlib/barh.py
termplotlib/figure.py
termplotlib/helpers.py
termplotlib/hist.py
termplotlib/plot.py
termplotlib/subplot.py
termplotlib-0.3.9.dist-info/LICENSE.txt
termplotlib-0.3.9.dist-info/METADATA
termplotlib-0.3.9.dist-info/WHEEL
termplotlib-0.3.9.dist-info/top_level.txt
termplotlib-0.3.9.dist-info/RECORD
