Metadata-Version: 2.1
Name: termplotlib
Version: 0.3.9
Summary: Python plotting for the command line
Home-page: https://github.com/nschloe/termplotlib
Author: Nico Schlömer
Author-email: nico.schloemer@gmail.com
License: GPL-3.0-or-later
Project-URL: Code, https://github.com/nschloe/termplotlib
Project-URL: Issues, https://github.com/nschloe/termplotlib/issues
Project-URL: Funding, https://github.com/sponsors/nschloe
Keywords: graphics,plotting,terminal,ascii,matplotlib
Platform: UNKNOWN
Classifier: Development Status :: 4 - Beta
Classifier: Environment :: Console
Classifier: Intended Audience :: Developers
Classifier: License :: OSI Approved :: GNU General Public License v3 or later (GPLv3+)
Classifier: Operating System :: OS Independent
Classifier: Programming Language :: Python
Classifier: Programming Language :: Python :: 3
Classifier: Programming Language :: Python :: 3.7
Classifier: Programming Language :: Python :: 3.8
Classifier: Programming Language :: Python :: 3.9
Classifier: Programming Language :: Python :: 3.10
Classifier: Topic :: System :: Shells
Classifier: Topic :: Multimedia :: Graphics
Requires-Python: >=3.7
License-File: LICENSE.txt
